pyserialsensors/__init__.py
pyserialsensors/core/__init__.py
pyserialsensors/core/comPortController.py
pyserialsensors/core/error.py
pyserialsensors/core/i2controller.py
pyserialsensors/core/i2cscan.py
pyserialsensors/core/sensor.py
pyserialsensors/core/toolbox.py
pyserialsensors/devices/FTDI.py
pyserialsensors/devices/MUX.py
pyserialsensors/devices/__init__.py
pyserialsensors/devices/ads1015.py
pyserialsensors/devices/bme280.py
pyserialsensors/devices/max31865.py
pyserialsensors/devices/nau7802.py
pyserialsensors/devices/qwiicrelay.py
pyserialsensors/devices/s8000.py
pyserialsensors/devices/scd30.py
pyserialsensors/devices/sdp8xx.py
pyserialsensors/devices/sfm3xxx.py
pyserialsensors/devices/shtxx.py
pyserialsensors/devices/smgair2.py
pyserialsensors/devices/sps30.py
pyserialsensors/examples/__init__.py
pyserialsensors/examples/example_clean_all_sps30.py
pyserialsensors/examples/example_mean.py
pyserialsensors/examples/example_single_read.py
pyserialsensors/examples/example_single_read_rtd.py
pyserialsensors/examples/example_uart.py
pyserialsensors/tests/__init__.py
pyserialsensors/tests/test_comPort.py
pyserialsensors/tests/test_sensor_bme280.py
pyserialsensors/tests/test_sensor_s8000.py
pyserialsensors/tests/test_sensor_sdp8.py
pyserialsensors/tests/test_sensor_smgair.py
pyserialsensors/tools/__init__.py
pyserialsensors/tools/bulk.py
pyserialsensors-0.10.0.dist-info/LICENSE
pyserialsensors-0.10.0.dist-info/METADATA
pyserialsensors-0.10.0.dist-info/WHEEL
pyserialsensors-0.10.0.dist-info/top_level.txt
pyserialsensors-0.10.0.dist-info/RECORD
